odoo8_addon_website_parameterized_snippet-8.0.1.0.0.99.dev10-py2.7-nspkg.pth
odoo8_addon_website_parameterized_snippet-8.0.1.0.0.99.dev10.dist-info/DESCRIPTION.rst
odoo8_addon_website_parameterized_snippet-8.0.1.0.0.99.dev10.dist-info/METADATA
odoo8_addon_website_parameterized_snippet-8.0.1.0.0.99.dev10.dist-info/RECORD
odoo8_addon_website_parameterized_snippet-8.0.1.0.0.99.dev10.dist-info/WHEEL
odoo8_addon_website_parameterized_snippet-8.0.1.0.0.99.dev10.dist-info/metadata.json
odoo8_addon_website_parameterized_snippet-8.0.1.0.0.99.dev10.dist-info/namespace_packages.txt
odoo8_addon_website_parameterized_snippet-8.0.1.0.0.99.dev10.dist-info/top_level.txt
odoo_addons/website_parameterized_snippet/README.rst
odoo_addons/website_parameterized_snippet/__init__.py
odoo_addons/website_parameterized_snippet/__openerp__.py
odoo_addons/website_parameterized_snippet/i18n/website_parameterized_snippet.pot
odoo_addons/website_parameterized_snippet/models/__init__.py
odoo_addons/website_parameterized_snippet/models/ir_qweb.py
odoo_addons/website_parameterized_snippet/models/view_view.py
odoo_addons/website_parameterized_snippet/static/description/icon.png
